odoo/addons/donation_direct_debit/README.rst
odoo/addons/donation_direct_debit/__init__.py
odoo/addons/donation_direct_debit/__manifest__.py
odoo/addons/donation_direct_debit/demo/donation_demo.xml
odoo/addons/donation_direct_debit/i18n/de.po
odoo/addons/donation_direct_debit/i18n/donation_direct_debit.pot
odoo/addons/donation_direct_debit/i18n/es.po
odoo/addons/donation_direct_debit/i18n/fr.po
odoo/addons/donation_direct_debit/i18n/it.po
odoo/addons/donation_direct_debit/models/__init__.py
odoo/addons/donation_direct_debit/models/account_journal.py
odoo/addons/donation_direct_debit/models/donation.py
odoo/addons/donation_direct_debit/readme/CONFIGURE.rst
odoo/addons/donation_direct_debit/readme/CONTRIBUTORS.rst
odoo/addons/donation_direct_debit/readme/DESCRIPTION.rst
odoo/addons/donation_direct_debit/readme/USAGE.rst
odoo/addons/donation_direct_debit/static/description/icon.png
odoo/addons/donation_direct_debit/static/description/index.html
odoo/addons/donation_direct_debit/tests/__init__.py
odoo/addons/donation_direct_debit/tests/test_direct_debit.py
odoo/addons/donation_direct_debit/views/account_journal.xml
odoo/addons/donation_direct_debit/views/donation.xml
odoo14_addon_donation_direct_debit-14.0.1.2.0.dist-info/METADATA
odoo14_addon_donation_direct_debit-14.0.1.2.0.dist-info/WHEEL
odoo14_addon_donation_direct_debit-14.0.1.2.0.dist-info/top_level.txt
odoo14_addon_donation_direct_debit-14.0.1.2.0.dist-info/RECORD
