Metadata-Version: 2.1
Name: odoo14-addon-donation_direct_debit
Version: 14.0.1.2.0
Summary: Auto-generate direct debit order on donation validation
Home-page: https://github.com/OCA/donation
Author: Akretion, Odoo Community Association (OCA)
Author-email: support@odoo-community.org
License: AGPL-3
Classifier: Programming Language :: Python
Classifier: Framework :: Odoo
Classifier: Framework :: Odoo :: 14.0
Classifier: License :: OSI Approved :: GNU Affero General Public License v3
Requires-Python: >=3.6
Requires-Dist: odoo14-addon-account-banking-sepa-direct-debit
Requires-Dist: odoo14-addon-donation
Requires-Dist: odoo<14.1dev,>=14.0a
